aiousbwatcher/__init__.py
aiousbwatcher/impl.py
aiousbwatcher/py.typed
aiousbwatcher-1.1.0.dist-info/LICENSE
aiousbwatcher-1.1.0.dist-info/METADATA
aiousbwatcher-1.1.0.dist-info/WHEEL
aiousbwatcher-1.1.0.dist-info/top_level.txt
aiousbwatcher-1.1.0.dist-info/RECORD
