Metadata-Version: 2.2
Name: aiousbwatcher
Version: 1.1.0
Summary: Watch for USB devices to be plugged and unplugged
Author-email: "J. Nick Koston" <bluetooth@koston.org>
License: MIT
Project-URL: Bug Tracker, https://github.com/bluetooth-devices/aiousbwatcher/issues
Project-URL: Changelog, https://github.com/bluetooth-devices/aiousbwatcher/blob/main/CHANGELOG.md
Project-URL: documentation, https://aiousbwatcher.readthedocs.io
Project-URL: repository, https://github.com/bluetooth-devices/aiousbwatcher
Classifier: Development Status :: 2 - Pre-Alpha
Classifier: Intended Audience :: Developers
Classifier: Natural Language :: English
Classifier: Operating System :: OS Independent
Classifier: Programming Language :: Python :: 3.12
Classifier: Programming Language :: Python :: 3.13
Classifier: Topic :: Software Development :: Libraries
Requires-Python: >=3.12
License-File: LICENSE
Requires-Dist: asyncinotify>=4.2.0
